pytest_layab/__init__.py
pytest_layab/flask.py
pytest_layab/version.py
pytest_layab-2.0.0.dist-info/LICENSE
pytest_layab-2.0.0.dist-info/METADATA
pytest_layab-2.0.0.dist-info/WHEEL
pytest_layab-2.0.0.dist-info/top_level.txt
pytest_layab-2.0.0.dist-info/RECORD
