Metadata-Version: 2.1
Name: pytest-layab
Version: 2.0.0
Summary: Pytest fixtures for layab.
Home-page: https://colin-b.github.io/pytest_layab/
Author: Colin Bounouar
Author-email: colin.bounouar.dev@gmail.com
Maintainer: Colin Bounouar
Maintainer-email: colin.bounouar.dev@gmail.com
License: MIT
Download-URL: https://pypi.org/project/pytest-layab/
Project-URL: GitHub, https://github.com/Colin-b/pytest_layab
Project-URL: Changelog, https://github.com/Colin-b/pytest_layab/blob/master/CHANGELOG.md
Project-URL: Issues, https://github.com/Colin-b/pytest_layab/issues
Keywords: test,layab,flask
Platform: Windows
Platform: Linux
Classifier: Development Status :: 5 - Production/Stable
Classifier: Intended Audience :: Developers
Classifier: License :: OSI Approved :: MIT License
Classifier: Natural Language :: English
Classifier: Programming Language :: Python
Classifier: Programming Language :: Python :: 3
Classifier: Programming Language :: Python :: 3.6
Classifier: Programming Language :: Python :: 3.7
Classifier: Programming Language :: Python :: 3.8
Classifier: Topic :: Software Development :: Build Tools
Requires-Python: >=3.6
Provides-Extra: testing
Requires-Dist: pytest-flask (==1.*) ; extra == 'testing'
Requires-Dist: pytest-cov (==2.*) ; extra == 'testing'
